regparse/__init__.py
regparse/__main__.py
regparse-1.0.1.dist-info/LICENSE.txt
regparse-1.0.1.dist-info/METADATA
regparse-1.0.1.dist-info/WHEEL
regparse-1.0.1.dist-info/top_level.txt
regparse-1.0.1.dist-info/RECORD
