Metadata-Version: 2.1
Name: regparse
Version: 1.0.1
Summary: Read exported windows registry text files
Home-page: https://github.com/Diverto/regparse
Author: Vlatko Kosturjak
Author-email: kost@diverto.hr
License: UNKNOWN
Platform: UNKNOWN
Classifier: Programming Language :: Python :: 3
Classifier: License :: OSI Approved :: MIT License
Classifier: Operating System :: OS Independent
